{
  "platformName": "igmovies",
  "logo": "logo.png",
  "instagramLink": "https://brainloom.com",
  "watchLink": "https://www.effectivegatecpm.com/tpc37vca?key=8914d20fd30b57b6f02cc09518647156",
  "content": [
    {
      "id": 1,
      "image": "1.jpg",
      "rating": 7.3,
      "language": "hindi",
      "year": 2005
    },
    {
      "id": 2,
      "image": "2.jpg",
      "rating": 8.1,
      "language": "hindi",
      "year": 2019
    },
    {
      "id": 3,
      "image": "3.jpg",
      "rating": 6.7,
      "language": "hindi",
      "year": 2012
    },
    {
      "id": 4,
      "image": "4.jpg",
      "rating": 9.2,
      "language": "hindi",
      "year": 2023
    },
    {
      "id": 5,
      "image": "5.jpg",
      "rating": 7.8,
      "language": "hindi",
      "year": 2008
    },
    {
      "id": 6,
      "image": "6.jpg",
      "rating": 6.4,
      "language": "hindi",
      "year": 2015
    },
    {
      "id": 7,
      "image": "7.jpg",
      "rating": 8.6,
      "language": "hindi",
      "year": 2021
    },
    {
      "id": 8,
      "image": "8.jpg",
      "rating": 7.1,
      "language": "hindi",
      "year": 2003
    },
    {
      "id": 9,
      "image": "9.jpg",
      "rating": 6.9,
      "language": "hindi",
      "year": 2018
    },
    {
      "id": 10,
      "image": "10.jpg",
      "rating": 8.9,
      "language": "hindi",
      "year": 2024
    },
    {
      "id": 11,
      "image": "11.jpg",
      "rating": 7.5,
      "language": "hindi",
      "year": 2007
    },
    {
      "id": 12,
      "image": "12.jpg",
      "rating": 6.8,
      "language": "hindi",
      "year": 2014
    },
    {
      "id": 13,
      "image": "13.jpg",
      "rating": 8.3,
      "language": "hindi",
      "year": 2020
    },
    {
      "id": 14,
      "image": "14.jpg",
      "rating": 7.0,
      "language": "hindi",
      "year": 2002
    },
    {
      "id": 15,
      "image": "15.jpg",
      "rating": 9.1,
      "language": "hindi",
      "year": 2025
    },
    {
      "id": 16,
      "image": "16.jpg",
      "rating": 6.5,
      "language": "hindi",
      "year": 2011
    },
    {
      "id": 17,
      "image": "17.jpg",
      "rating": 8.4,
      "language": "hindi",
      "year": 2017
    },
    {
      "id": 18,
      "image": "18.jpg",
      "rating": 7.7,
      "language": "hindi",
      "year": 2006
    },
    {
      "id": 19,
      "image": "19.jpg",
      "rating": 6.2,
      "language": "hindi",
      "year": 2013
    },
    {
      "id": 20,
      "image": "20.jpg",
      "rating": 8.7,
      "language": "hindi",
      "year": 2022
    },
    {
      "id": 21,
      "image": "21.jpg",
      "rating": 7.4,
      "language": "hindi",
      "year": 2004
    },
    {
      "id": 22,
      "image": "22.jpg",
      "rating": 9.0,
      "language": "hindi",
      "year": 2016
    },
    {
      "id": 23,
      "image": "23.jpg",
      "rating": 6.6,
      "language": "hindi",
      "year": 2009
    },
    {
      "id": 24,
      "image": "24.jpg",
      "rating": 8.2,
      "language": "hindi",
      "year": 2010
    },
    {
      "id": 25,
      "image": "25.jpg",
      "rating": 7.9,
      "language": "hindi",
      "year": 2001
    },
    {
      "id": 26,
      "image": "26.jpg",
      "rating": 6.3,
      "language": "hindi",
      "year": 1998
    },
    {
      "id": 27,
      "image": "27.jpg",
      "rating": 8.8,
      "language": "hindi",
      "year": 2000
    },
    {
      "id": 28,
      "image": "28.jpg",
      "rating": 7.2,
      "language": "hindi",
      "year": 1999
    },
    {
      "id": 29,
      "image": "29.jpg",
      "rating": 9.3,
      "language": "hindi",
      "year": 2023
    },
    {
      "id": 30,
      "image": "30.jpg",
      "rating": 6.1,
      "language": "hindi",
      "year": 2012
    },
    {
      "id": 31,
      "image": "31.jpg",
      "rating": 8.5,
      "language": "hindi",
      "year": 2019
    },
    {
      "id": 32,
      "image": "32.jpg",
      "rating": 7.6,
      "language": "hindi",
      "year": 2005
    },
    {
      "id": 33,
      "image": "33.jpg",
      "rating": 6.9,
      "language": "hindi",
      "year": 2018
    },
    {
      "id": 34,
      "image": "34.jpg",
      "rating": 8.0,
      "language": "hindi",
      "year": 2021
    },
    {
      "id": 35,
      "image": "35.jpg",
      "rating": 7.1,
      "language": "hindi",
      "year": 2007
    },
    {
      "id": 36,
      "image": "36.jpg",
      "rating": 9.4,
      "language": "hindi",
      "year": 2024
    },
    {
      "id": 37,
      "image": "37.jpg",
      "rating": 6.8,
      "language": "hindi",
      "year": 2014
    },
    {
      "id": 38,
      "image": "38.jpg",
      "rating": 8.3,
      "language": "hindi",
      "year": 2020
    },
    {
      "id": 39,
      "image": "39.jpg",
      "rating": 7.5,
      "language": "hindi",
      "year": 2003
    },
    {
      "id": 40,
      "image": "40.jpg",
      "rating": 6.7,
      "language": "hindi",
      "year": 2011
    },
    {
      "id": 41,
      "image": "41.jpg",
      "rating": 8.9,
      "language": "hindi",
      "year": 2022
    },
    {
      "id": 42,
      "image": "42.jpg",
      "rating": 7.3,
      "language": "hindi",
      "year": 2006
    },
    {
      "id": 43,
      "image": "43.jpg",
      "rating": 9.0,
      "language": "hindi",
      "year": 2025
    },
    {
      "id": 44,
      "image": "44.jpg",
      "rating": 6.5,
      "language": "hindi",
      "year": 2013
    },
    {
      "id": 45,
      "image": "45.jpg",
      "rating": 8.2,
      "language": "hindi",
      "year": 2017
    },
    {
      "id": 46,
      "image": "46.jpg",
      "rating": 7.8,
      "language": "hindi",
      "year": 2004
    },
    {
      "id": 47,
      "image": "47.jpg",
      "rating": 6.4,
      "language": "hindi",
      "year": 2010
    },
    {
      "id": 48,
      "image": "48.jpg",
      "rating": 8.6,
      "language": "hindi",
      "year": 2016
    },
    {
      "id": 49,
      "image": "49.jpg",
      "rating": 7.2,
      "language": "hindi",
      "year": 2002
    },
    {
      "id": 50,
      "image": "50.jpg",
      "rating": 9.1,
      "language": "hindi",
      "year": 2023
    },
    {
      "id": 51,
      "image": "51.jpg",
      "rating": 6.9,
      "language": "hindi",
      "year": 2009
    },
    {
      "id": 52,
      "image": "52.jpg",
      "rating": 8.4,
      "language": "hindi",
      "year": 2015
    },
    {
      "id": 53,
      "image": "53.jpg",
      "rating": 7.7,
      "language": "hindi",
      "year": 2001
    },
    {
      "id": 54,
      "image": "54.jpg",
      "rating": 6.3,
      "language": "hindi",
      "year": 1998
    },
    {
      "id": 55,
      "image": "55.jpg",
      "rating": 8.8,
      "language": "hindi",
      "year": 2000
    },
    {
      "id": 56,
      "image": "56.jpg",
      "rating": 7.4,
      "language": "hindi",
      "year": 1999
    },
    {
      "id": 57,
      "image": "57.jpg",
      "rating": 9.2,
      "language": "hindi",
      "year": 2012
    },
    {
      "id": 58,
      "image": "58.jpg",
      "rating": 6.6,
      "language": "hindi",
      "year": 2019
    },
    {
      "id": 59,
      "image": "59.jpg",
      "rating": 8.1,
      "language": "hindi",
      "year": 2021
    },
    {
      "id": 60,
      "image": "60.jpg",
      "rating": 7.9,
      "language": "hindi",
      "year": 2005
    },
    {
      "id": 61,
      "image": "61.jpg",
      "rating": 6.2,
      "language": "hindi",
      "year": 2018
    },
    {
      "id": 62,
      "image": "62.jpg",
      "rating": 8.7,
      "language": "hindi",
      "year": 2024
    },
    {
      "id": 63,
      "image": "63.jpg",
      "rating": 7.6,
      "language": "hindi",
      "year": 2007
    },
    {
      "id": 64,
      "image": "64.jpg",
      "rating": 9.3,
      "language": "hindi",
      "year": 2014
    },
    {
      "id": 65,
      "image": "65.jpg",
      "rating": 6.8,
      "language": "hindi",
      "year": 2020
    },
    {
      "id": 66,
      "image": "66.jpg",
      "rating": 8.0,
      "language": "hindi",
      "year": 2003
    },
    {
      "id": 67,
      "image": "67.jpg",
      "rating": 7.1,
      "language": "hindi",
      "year": 2011
    },
    {
      "id": 68,
      "image": "68.jpg",
      "rating": 6.5,
      "language": "hindi",
      "year": 2022
    },
    {
      "id": 69,
      "image": "69.jpg",
      "rating": 8.9,
      "language": "hindi",
      "year": 2006
    },
    {
      "id": 70,
      "image": "70.jpg",
      "rating": 7.3,
      "language": "hindi",
      "year": 2025
    },
    {
      "id": 71,
      "image": "71.jpg",
      "rating": 9.0,
      "language": "hindi",
      "year": 2013
    },
    {
      "id": 72,
      "image": "72.jpg",
      "rating": 6.7,
      "language": "hindi",
      "year": 2017
    },
    {
      "id": 73,
      "image": "73.jpg",
      "rating": 8.5,
      "language": "hindi",
      "year": 2004
    },
    {
      "id": 74,
      "image": "74.jpg",
      "rating": 7.8,
      "language": "hindi",
      "year": 2010
    },
    {
      "id": 75,
      "image": "75.jpg",
      "rating": 6.4,
      "language": "hindi",
      "year": 2016
    },
    {
      "id": 76,
      "image": "76.jpg",
      "rating": 8.2,
      "language": "hindi",
      "year": 2002
    },
    {
      "id": 77,
      "image": "77.jpg",
      "rating": 7.5,
      "language": "hindi",
      "year": 2023
    },
    {
      "id": 78,
      "image": "78.jpg",
      "rating": 9.1,
      "language": "hindi",
      "year": 2009
    },
    {
      "id": 79,
      "image": "79.jpg",
      "rating": 6.9,
      "language": "hindi",
      "year": 2015
    },
    {
      "id": 80,
      "image": "80.jpg",
      "rating": 8.3,
      "language": "hindi",
      "year": 2001
    },
    {
      "id": 81,
      "image": "81.jpg",
      "rating": 7.7,
      "language": "hindi",
      "year": 1998
    },
    {
      "id": 82,
      "image": "82.jpg",
      "rating": 6.3,
      "language": "hindi",
      "year": 2000
    },
    {
      "id": 83,
      "image": "83.jpg",
      "rating": 8.6,
      "language": "hindi",
      "year": 1999
    },
    {
      "id": 84,
      "image": "84.jpg",
      "rating": 7.4,
      "language": "hindi",
      "year": 2012
    },
    {
      "id": 85,
      "image": "85.jpg",
      "rating": 9.2,
      "language": "hindi",
      "year": 2019
    },
    {
      "id": 86,
      "image": "86.jpg",
      "rating": 6.8,
      "language": "hindi",
      "year": 2021
    },
    {
      "id": 87,
      "image": "87.jpg",
      "rating": 8.1,
      "language": "hindi",
      "year": 2005
    },
    {
      "id": 88,
      "image": "88.jpg",
      "rating": 7.9,
      "language": "hindi",
      "year": 2018
    },
    {
      "id": 89,
      "image": "89.jpg",
      "rating": 6.5,
      "language": "hindi",
      "year": 2024
    },
    {
      "id": 90,
      "image": "90.jpg",
      "rating": 8.7,
      "language": "hindi",
      "year": 2007
    },
    {
      "id": 91,
      "image": "91.jpg",
      "rating": 7.2,
      "language": "hindi",
      "year": 2014
    },
    {
      "id": 92,
      "image": "92.jpg",
      "rating": 9.4,
      "language": "hindi",
      "year": 2020
    },
    {
      "id": 93,
      "image": "93.jpg",
      "rating": 6.6,
      "language": "hindi",
      "year": 2003
    },
    {
      "id": 94,
      "image": "94.jpg",
      "rating": 8.4,
      "language": "hindi",
      "year": 2011
    },
    {
      "id": 95,
      "image": "95.jpg",
      "rating": 7.0,
      "language": "hindi",
      "year": 2022
    },
    {
      "id": 96,
      "image": "96.jpg",
      "rating": 6.9,
      "language": "hindi",
      "year": 2006
    },
    {
      "id": 97,
      "image": "97.jpg",
      "rating": 8.8,
      "language": "hindi",
      "year": 2025
    },
    {
      "id": 98,
      "image": "98.jpg",
      "rating": 7.5,
      "language": "hindi",
      "year": 2013
    },
    {
      "id": 99,
      "image": "99.jpg",
      "rating": 9.0,
      "language": "hindi",
      "year": 2017
    },
    {
      "id": 100,
      "image": "100.jpg",
      "rating": 6.7,
      "language": "hindi",
      "year": 2004
    },
    {
      "id": 101,
      "image": "101.jpg",
      "rating": 8.3,
      "language": "hindi",
      "year": 2010
    },
    {
      "id": 102,
      "image": "102.jpg",
      "rating": 7.8,
      "language": "hindi",
      "year": 2016
    },
    {
      "id": 103,
      "image": "103.jpg",
      "rating": 6.4,
      "language": "hindi",
      "year": 2002
    },
    {
      "id": 104,
      "image": "104.jpg",
      "rating": 8.9,
      "language": "hindi",
      "year": 2023
    },
    {
      "id": 105,
      "image": "105.jpg",
      "rating": 7.6,
      "language": "hindi",
      "year": 2009
    },
    {
      "id": 106,
      "image": "106.jpg",
      "rating": 9.1,
      "language": "hindi",
      "year": 2015
    },
    {
      "id": 107,
      "image": "107.jpg",
      "rating": 6.8,
      "language": "hindi",
      "year": 2001
    },
    {
      "id": 108,
      "image": "108.jpg",
      "rating": 8.2,
      "language": "hindi",
      "year": 1998
    },
    {
      "id": 109,
      "image": "109.jpg",
      "rating": 7.3,
      "language": "hindi",
      "year": 2000
    },
    {
      "id": 110,
      "image": "110.jpg",
      "rating": 6.5,
      "language": "hindi",
      "year": 1999
    },
    {
      "id": 111,
      "image": "111.jpg",
      "rating": 8.6,
      "language": "hindi",
      "year": 2012
    },
    {
      "id": 112,
      "image": "112.jpg",
      "rating": 7.9,
      "language": "hindi",
      "year": 2019
    },
    {
      "id": 113,
      "image": "113.jpg",
      "rating": 9.3,
      "language": "hindi",
      "year": 2021
    },
    {
      "id": 114,
      "image": "114.jpg",
      "rating": 6.7,
      "language": "hindi",
      "year": 2005
    },
    {
      "id": 115,
      "image": "115.jpg",
      "rating": 8.0,
      "language": "hindi",
      "year": 2018
    },
    {
      "id": 116,
      "image": "116.jpg",
      "rating": 7.4,
      "language": "hindi",
      "year": 2024
    },
    {
      "id": 117,
      "image": "117.jpg",
      "rating": 6.9,
      "language": "hindi",
      "year": 2007
    },
    {
      "id": 118,
      "image": "118.jpg",
      "rating": 8.5,
      "language": "hindi",
      "year": 2014
    },
    {
      "id": 119,
      "image": "119.jpg",
      "rating": 7.1,
      "language": "hindi",
      "year": 2020
    },
    {
      "id": 120,
      "image": "120.jpg",
      "rating": 9.2,
      "language": "hindi",
      "year": 2003
    },
    {
      "id": 121,
      "image": "121.jpg",
      "rating": 6.6,
      "language": "hindi",
      "year": 2011
    },
    {
      "id": 122,
      "image": "122.jpg",
      "rating": 8.4,
      "language": "hindi",
      "year": 2022
    },
    {
      "id": 123,
      "image": "123.jpg",
      "rating": 7.7,
      "language": "hindi",
      "year": 2006
    },
    {
      "id": 124,
      "image": "124.jpg",
      "rating": 6.3,
      "language": "hindi",
      "year": 2025
    },
    {
      "id": 125,
      "image": "125.jpg",
      "rating": 8.8,
      "language": "hindi",
      "year": 2013
    },
    {
      "id": 126,
      "image": "126.jpg",
      "rating": 7.5,
      "language": "hindi",
      "year": 2017
    },
    {
      "id": 127,
      "image": "127.jpg",
      "rating": 9.0,
      "language": "hindi",
      "year": 2004
    },
    {
      "id": 128,
      "image": "128.jpg",
      "rating": 6.8,
      "language": "hindi",
      "year": 2010
    },
    {
      "id": 129,
      "image": "129.jpg",
      "rating": 8.1,
      "language": "hindi",
      "year": 2016
    },
    {
      "id": 130,
      "image": "130.jpg",
      "rating": 7.2,
      "language": "hindi",
      "year": 2002
    },
    {
      "id": 131,
      "image": "131.jpg",
      "rating": 6.4,
      "language": "hindi",
      "year": 2023
    },
    {
      "id": 132,
      "image": "132.jpg",
      "rating": 8.7,
      "language": "hindi",
      "year": 2009
    },
    {
      "id": 133,
      "image": "133.jpg",
      "rating": 7.9,
      "language": "hindi",
      "year": 2015
    },
    {
      "id": 134,
      "image": "134.jpg",
      "rating": 9.4,
      "language": "hindi",
      "year": 2001
    },
    {
      "id": 135,
      "image": "135.jpg",
      "rating": 6.5,
      "language": "hindi",
      "year": 1998
    },
    {
      "id": 136,
      "image": "136.jpg",
      "rating": 8.3,
      "language": "hindi",
      "year": 2000
    },
    {
      "id": 137,
      "image": "137.jpg",
      "rating": 7.6,
      "language": "hindi",
      "year": 1999
    },
    {
      "id": 138,
      "image": "138.jpg",
      "rating": 6.9,
      "language": "hindi",
      "year": 2012
    },
    {
      "id": 139,
      "image": "139.jpg",
      "rating": 8.9,
      "language": "hindi",
      "year": 2019
    },
    {
      "id": 140,
      "image": "140.jpg",
      "rating": 7.3,
      "language": "hindi",
      "year": 2021
    },
    {
      "id": 141,
      "image": "141.jpg",
      "rating": 9.1,
      "language": "hindi",
      "year": 2005
    },
    {
      "id": 142,
      "image": "142.jpg",
      "rating": 6.7,
      "language": "hindi",
      "year": 2018
    },
    {
      "id": 143,
      "image": "143.jpg",
      "rating": 8.2,
      "language": "hindi",
      "year": 2024
    },
    {
      "id": 144,
      "image": "144.jpg",
      "rating": 7.8,
      "language": "hindi",
      "year": 2007
    },
    {
      "id": 145,
      "image": "145.jpg",
      "rating": 6.4,
      "language": "hindi",
      "year": 2014
    },
    {
      "id": 146,
      "image": "146.jpg",
      "rating": 8.6,
      "language": "hindi",
      "year": 2020
    },
    {
      "id": 147,
      "image": "147.jpg",
      "rating": 7.5,
      "language": "hindi",
      "year": 2003
    },
    {
      "id": 148,
      "image": "148.jpg",
      "rating": 9.0,
      "language": "hindi",
      "year": 2011
    },
    {
      "id": 149,
      "image": "149.jpg",
      "rating": 6.8,
      "language": "hindi",
      "year": 2022
    },
    {
      "id": 150,
      "image": "150.jpg",
      "rating": 8.4,
      "language": "hindi",
      "year": 2006
    },
    {
      "id": 151,
      "image": "151.jpg",
      "rating": 7.1,
      "language": "hindi",
      "year": 2025
    },
    {
      "id": 152,
      "image": "152.jpg",
      "rating": 6.6,
      "language": "hindi",
      "year": 2013
    },
    {
      "id": 153,
      "image": "153.jpg",
      "rating": 8.8,
      "language": "hindi",
      "year": 2017
    },
    {
      "id": 154,
      "image": "154.jpg",
      "rating": 7.9,
      "language": "hindi",
      "year": 2004
    },
    {
      "id": 155,
      "image": "155.jpg",
      "rating": 9.3,
      "language": "hindi",
      "year": 2010
    },
    {
      "id": 156,
      "image": "156.jpg",
      "rating": 6.5,
      "language": "hindi",
      "year": 2016
    },
    {
      "id": 157,
      "image": "157.jpg",
      "rating": 8.1,
      "language": "hindi",
      "year": 2002
    },
    {
      "id": 158,
      "image": "158.jpg",
      "rating": 7.4,
      "language": "hindi",
      "year": 2023
    },
    {
      "id": 159,
      "image": "159.jpg",
      "rating": 6.9,
      "language": "hindi",
      "year": 2009
    },
    {
      "id": 160,
      "image": "160.jpg",
      "rating": 8.7,
      "language": "hindi",
      "year": 2015
    },
    {
      "id": 161,
      "image": "161.jpg",
      "rating": 7.6,
      "language": "hindi",
      "year": 2001
    },
    {
      "id": 162,
      "image": "162.jpg",
      "rating": 9.2,
      "language": "hindi",
      "year": 1998
    },
    {
      "id": 163,
      "image": "163.jpg",
      "rating": 6.7,
      "language": "hindi",
      "year": 2000
    },
    {
      "id": 164,
      "image": "164.jpg",
      "rating": 8.5,
      "language": "hindi",
      "year": 1999
    },
    {
      "id": 165,
      "image": "165.jpg",
      "rating": 7.3,
      "language": "hindi",
      "year": 2012
    },
    {
      "id": 166,
      "image": "166.jpg",
      "rating": 6.8,
      "language": "hindi",
      "year": 2019
    },
    {
      "id": 167,
      "image": "167.jpg",
      "rating": 8.9,
      "language": "hindi",
      "year": 2021
    },
    {
      "id": 168,
      "image": "168.jpg",
      "rating": 7.7,
      "language": "hindi",
      "year": 2005
    },
    {
      "id": 169,
      "image": "169.jpg",
      "rating": 9.0,
      "language": "hindi",
      "year": 2018
    },
    {
      "id": 170,
      "image": "170.jpg",
      "rating": 6.4,
      "language": "hindi",
      "year": 2024
    },
    {
      "id": 171,
      "image": "171.jpg",
      "rating": 8.3,
      "language": "hindi",
      "year": 2007
    },
    {
      "id": 172,
      "image": "172.jpg",
      "rating": 7.8,
      "language": "hindi",
      "year": 2014
    },
    {
      "id": 173,
      "image": "173.jpg",
      "rating": 6.6,
      "language": "hindi",
      "year": 2020
    },
    {
      "id": 174,
      "image": "174.jpg",
      "rating": 8.6,
      "language": "hindi",
      "year": 2003
    },
    {
      "id": 175,
      "image": "175.jpg",
      "rating": 7.5,
      "language": "hindi",
      "year": 2011
    },
    {
      "id": 176,
      "image": "176.jpg",
      "rating": 9.1,
      "language": "hindi",
      "year": 2022
    },
    {
      "id": 177,
      "image": "177.jpg",
      "rating": 6.9,
      "language": "hindi",
      "year": 2006
    },
    {
      "id": 178,
      "image": "178.jpg",
      "rating": 8.2,
      "language": "hindi",
      "year": 2025
    },
    {
      "id": 179,
      "image": "179.jpg",
      "rating": 7.4,
      "language": "hindi",
      "year": 2013
    },
    {
      "id": 180,
      "image": "180.jpg",
      "rating": 6.7,
      "language": "hindi",
      "year": 2017
    },
    {
      "id": 181,
      "image": "181.jpg",
      "rating": 8.8,
      "language": "hindi",
      "year": 2004
    },
    {
      "id": 182,
      "image": "182.jpg",
      "rating": 7.9,
      "language": "hindi",
      "year": 2010
    },
    {
      "id": 183,
      "image": "183.jpg",
      "rating": 9.4,
      "language": "hindi",
      "year": 2016
    },
    {
      "id": 184,
      "image": "184.jpg",
      "rating": 6.5,
      "language": "hindi",
      "year": 2002
    },
    {
      "id": 185,
      "image": "185.jpg",
      "rating": 8.0,
      "language": "hindi",
      "year": 2023
    },
    {
      "id": 186,
      "image": "186.jpg",
      "rating": 7.3,
      "language": "hindi",
      "year": 2009
    },
    {
      "id": 187,
      "image": "187.jpg",
      "rating": 6.8,
      "language": "hindi",
      "year": 2015
    },
    {
      "id": 188,
      "image": "188.jpg",
      "rating": 8.7,
      "language": "hindi",
      "year": 2001
    },
    {
      "id": 189,
      "image": "189.jpg",
      "rating": 7.6,
      "language": "hindi",
      "year": 1998
    },
    {
      "id": 190,
      "image": "190.jpg",
      "rating": 9.2,
      "language": "hindi",
      "year": 2000
    },
    {
      "id": 191,
      "image": "191.jpg",
      "rating": 6.4,
      "language": "hindi",
      "year": 1999
    },
    {
      "id": 192,
      "image": "192.jpg",
      "rating": 8.4,
      "language": "hindi",
      "year": 2012
    },
    {
      "id": 193,
      "image": "193.jpg",
      "rating": 7.7,
      "language": "hindi",
      "year": 2019
    },
    {
      "id": 194,
      "image": "194.jpg",
      "rating": 6.9,
      "language": "hindi",
      "year": 2021
    },
    {
      "id": 195,
      "image": "195.jpg",
      "rating": 8.5,
      "language": "hindi",
      "year": 2005
    },
    {
      "id": 196,
      "image": "196.jpg",
      "rating": 7.2,
      "language": "hindi",
      "year": 2018
    },
    {
      "id": 197,
      "image": "197.jpg",
      "rating": 9.0,
      "language": "hindi",
      "year": 2024
    },
    {
      "id": 198,
      "image": "198.jpg",
      "rating": 6.6,
      "language": "hindi",
      "year": 2007
    },
    {
      "id": 199,
      "image": "199.jpg",
      "rating": 8.3,
      "language": "hindi",
      "year": 2014
    },
    {
      "id": 200,
      "image": "200.jpg",
      "rating": 7.8,
      "language": "hindi",
      "year": 2020
    },
    {
      "id": 201,
      "image": "201.jpg",
      "rating": 9.1,
      "language": "hindi",
      "year": 2003
    },
    {
      "id": 202,
      "image": "202.jpg",
      "rating": 6.7,
      "language": "hindi",
      "year": 2011
    },
    {
      "id": 203,
      "image": "203.jpg",
      "rating": 8.6,
      "language": "hindi",
      "year": 2022
    },
    {
      "id": 204,
      "image": "204.jpg",
      "rating": 7.5,
      "language": "hindi",
      "year": 2006
    },
    {
      "id": 205,
      "image": "205.jpg",
      "rating": 6.8,
      "language": "hindi",
      "year": 2025
    },
    {
      "id": 206,
      "image": "206.jpg",
      "rating": 8.9,
      "language": "hindi",
      "year": 2013
    },
    {
      "id": 207,
      "image": "207.jpg",
      "rating": 7.4,
      "language": "hindi",
      "year": 2017
    },
    {
      "id": 208,
      "image": "208.jpg",
      "rating": 9.3,
      "language": "hindi",
      "year": 2004
    },
    {
      "id": 209,
      "image": "209.jpg",
      "rating": 6.5,
      "language": "hindi",
      "year": 2010
    },
    {
      "id": 210,
      "image": "210.jpg",
      "rating": 8.2,
      "language": "hindi",
      "year": 2016
    },
    {
      "id": 211,
      "image": "211.jpg",
      "rating": 7.9,
      "language": "hindi",
      "year": 2002
    },
    {
      "id": 212,
      "image": "212.jpg",
      "rating": 6.4,
      "language": "hindi",
      "year": 2023
    },
    {
      "id": 213,
      "image": "213.jpg",
      "rating": 8.7,
      "language": "hindi",
      "year": 2009
    },
    {
      "id": 214,
      "image": "214.jpg",
      "rating": 7.6,
      "language": "hindi",
      "year": 2015
    },
    {
      "id": 215,
      "image": "215.jpg",
      "rating": 9.4,
      "language": "hindi",
      "year": 2001
    },
    {
      "id": 216,
      "image": "216.jpg",
      "rating": 6.9,
      "language": "hindi",
      "year": 1998
    },
    {
      "id": 217,
      "image": "217.jpg",
      "rating": 8.1,
      "language": "hindi",
      "year": 2000
    },
    {
      "id": 218,
      "image": "218.jpg",
      "rating": 7.3,
      "language": "hindi",
      "year": 1999
    },
    {
      "id": 219,
      "image": "219.jpg",
      "rating": 6.7,
      "language": "hindi",
      "year": 2012
    },
    {
      "id": 220,
      "image": "220.jpg",
      "rating": 8.8,
      "language": "hindi",
      "year": 2019
    },
    {
      "id": 221,
      "image": "221.jpg",
      "rating": 7.8,
      "language": "hindi",
      "year": 2021
    },
    {
      "id": 222,
      "image": "222.jpg",
      "rating": 9.0,
      "language": "hindi",
      "year": 2005
    },
    {
      "id": 223,
      "image": "223.jpg",
      "rating": 6.6,
      "language": "hindi",
      "year": 2018
    },
    {
      "id": 224,
      "image": "224.jpg",
      "rating": 8.4,
      "language": "hindi",
      "year": 2024
    },
    {
      "id": 225,
      "image": "225.jpg",
      "rating": 7.5,
      "language": "hindi",
      "year": 2007
    },
    {
      "id": 226,
      "image": "226.jpg",
      "rating": 6.8,
      "language": "hindi",
      "year": 2014
    },
    {
      "id": 227,
      "image": "227.jpg",
      "rating": 8.9,
      "language": "hindi",
      "year": 2020
    },
    {
      "id": 228,
      "image": "228.jpg",
      "rating": 7.7,
      "language": "hindi",
      "year": 2003
    },
    {
      "id": 229,
      "image": "229.jpg",
      "rating": 9.2,
      "language": "hindi",
      "year": 2011
    },
    {
      "id": 230,
      "image": "230.jpg",
      "rating": 6.5,
      "language": "hindi",
      "year": 2022
    },
    {
      "id": 231,
      "image": "231.jpg",
      "rating": 8.3,
      "language": "hindi",
      "year": 2006
    },
    {
      "id": 232,
      "image": "232.jpg",
      "rating": 7.4,
      "language": "hindi",
      "year": 2025
    },
    {
      "id": 233,
      "image": "233.jpg",
      "rating": 6.9,
      "language": "hindi",
      "year": 2013
    },
    {
      "id": 234,
      "image": "234.jpg",
      "rating": 8.6,
      "language": "hindi",
      "year": 2017
    },
    {
      "id": 235,
      "image": "235.jpg",
      "rating": 7.9,
      "language": "hindi",
      "year": 2004
    },
    {
      "id": 236,
      "image": "236.jpg",
      "rating": 9.1,
      "language": "hindi",
      "year": 2010
    },
    {
      "id": 237,
      "image": "237.jpg",
      "rating": 6.7,
      "language": "hindi",
      "year": 2016
    },
    {
      "id": 238,
      "image": "238.jpg",
      "rating": 8.5,
      "language": "hindi",
      "year": 2002
    },
    {
      "id": 239,
      "image": "239.jpg",
      "rating": 7.6,
      "language": "hindi",
      "year": 2023
    },
    {
      "id": 240,
      "image": "240.jpg",
      "rating": 6.8,
      "language": "hindi",
      "year": 2009
    },
    {
      "id": 241,
      "image": "241.jpg",
      "rating": 8.7,
      "language": "hindi",
      "year": 2015
    },
    {
      "id": 242,
      "image": "242.jpg",
      "rating": 7.3,
      "language": "hindi",
      "year": 2001
    },
    {
      "id": 243,
      "image": "243.jpg",
      "rating": 9.0,
      "language": "hindi",
      "year": 1998
    },
    {
      "id": 244,
      "image": "244.jpg",
      "rating": 6.6,
      "language": "hindi",
      "year": 2000
    },
    {
      "id": 245,
      "image": "245.jpg",
      "rating": 8.4,
      "language": "hindi",
      "year": 1999
    },
    {
      "id": 246,
      "image": "246.jpg",
      "rating": 7.8,
      "language": "hindi",
      "year": 2012
    },
    {
      "id": 247,
      "image": "247.jpg",
      "rating": 6.9,
      "language": "hindi",
      "year": 2019
    },
    {
      "id": 248,
      "image": "248.jpg",
      "rating": 8.8,
      "language": "hindi",
      "year": 2021
    },
    {
      "id": 249,
      "image": "249.jpg",
      "rating": 7.5,
      "language": "hindi",
      "year": 2005
    },
    {
      "id": 250,
      "image": "250.jpg",
      "rating": 9.3,
      "language": "hindi",
      "year": 2018
    },
    {
      "id": 251,
      "image": "251.jpg",
      "rating": 6.7,
      "language": "hindi",
      "year": 2024
    },
    {
      "id": 252,
      "image": "252.jpg",
      "rating": 8.2,
      "language": "hindi",
      "year": 2007
    },
    {
      "id": 253,
      "image": "253.jpg",
      "rating": 7.9,
      "language": "hindi",
      "year": 2014
    },
    {
      "id": 254,
      "image": "254.jpg",
      "rating": 6.5,
      "language": "hindi",
      "year": 2020
    },
    {
      "id": 255,
      "image": "255.jpg",
      "rating": 8.6,
      "language": "hindi",
      "year": 2003
    },
    {
      "id": 256,
      "image": "256.jpg",
      "rating": 7.4,
      "language": "hindi",
      "year": 2011
    },
    {
      "id": 257,
      "image": "257.jpg",
      "rating": 9.1,
      "language": "hindi",
      "year": 2022
    },
    {
      "id": 258,
      "image": "258.jpg",
      "rating": 6.8,
      "language": "hindi",
      "year": 2006
    },
    {
      "id": 259,
      "image": "259.jpg",
      "rating": 8.3,
      "language": "hindi",
      "year": 2025
    },
    {
      "id": 260,
      "image": "260.jpg",
      "rating": 7.7,
      "language": "hindi",
      "year": 2013
    },
    {
      "id": 261,
      "image": "261.jpg",
      "rating": 6.9,
      "language": "hindi",
      "year": 2017
    },
    {
      "id": 262,
      "image": "262.jpg",
      "rating": 8.9,
      "language": "hindi",
      "year": 2004
    },
    {
      "id": 263,
      "image": "263.jpg",
      "rating": 7.6,
      "language": "hindi",
      "year": 2010
    },
    {
      "id": 264,
      "image": "264.jpg",
      "rating": 9.2,
      "language": "hindi",
      "year": 2016
    },
    {
      "id": 265,
      "image": "265.jpg",
      "rating": 6.7,
      "language": "hindi",
      "year": 2002
    },
    {
      "id": 266,
      "image": "266.jpg",
      "rating": 8.5,
      "language": "hindi",
      "year": 2023
    },
    {
      "id": 267,
      "image": "267.jpg",
      "rating": 7.8,
      "language": "hindi",
      "year": 2009
    },
    {
      "id": 268,
      "image": "268.jpg",
      "rating": 6.4,
      "language": "hindi",
      "year": 2015
    },
    {
      "id": 269,
      "image": "269.jpg",
      "rating": 8.7,
      "language": "hindi",
      "year": 2001
    },
    {
      "id": 270,
      "image": "270.jpg",
      "rating": 7.5,
      "language": "hindi",
      "year": 1998
    },
    {
      "id": 271,
      "image": "271.jpg",
      "rating": 9.0,
      "language": "hindi",
      "year": 2000
    },
    {
      "id": 272,
      "image": "272.jpg",
      "rating": 6.6,
      "language": "hindi",
      "year": 1999
    },
    {
      "id": 273,
      "image": "273.jpg",
      "rating": 8.4,
      "language": "hindi",
      "year": 2012
    },
    {
      "id": 274,
      "image": "274.jpg",
      "rating": 7.9,
      "language": "hindi",
      "year": 2019
    },
    {
      "id": 275,
      "image": "275.jpg",
      "rating": 6.8,
      "language": "hindi",
      "year": 2021
    },
    {
      "id": 276,
      "image": "276.jpg",
      "rating": 8.6,
      "language": "hindi",
      "year": 2005
    },
    {
      "id": 277,
      "image": "277.jpg",
      "rating": 7.4,
      "language": "hindi",
      "year": 2018
    },
    {
      "id": 278,
      "image": "278.jpg",
      "rating": 9.3,
      "language": "hindi",
      "year": 2024
    },
    {
      "id": 279,
      "image": "279.jpg",
      "rating": 6.7,
      "language": "hindi",
      "year": 2007
    },
    {
      "id": 280,
      "image": "280.jpg",
      "rating": 8.2,
      "language": "hindi",
      "year": 2014
    },
    {
      "id": 281,
      "image": "281.jpg",
      "rating": 7.8,
      "language": "hindi",
      "year": 2020
    },
    {
      "id": 282,
      "image": "282.jpg",
      "rating": 6.5,
      "language": "hindi",
      "year": 2003
    },
    {
      "id": 283,
      "image": "283.jpg",
      "rating": 8.9,
      "language": "hindi",
      "year": 2011
    },
    {
      "id": 284,
      "image": "284.jpg",
      "rating": 7.6,
      "language": "hindi",
      "year": 2022
    },
    {
      "id": 285,
      "image": "285.jpg",
      "rating": 9.1,
      "language": "hindi",
      "year": 2006
    },
    {
      "id": 286,
      "image": "286.jpg",
      "rating": 6.9,
      "language": "hindi",
      "year": 2025
    },
    {
      "id": 287,
      "image": "287.jpg",
      "rating": 8.3,
      "language": "hindi",
      "year": 2013
    },
    {
      "id": 288,
      "image": "288.jpg",
      "rating": 7.7,
      "language": "hindi",
      "year": 2017
    },
    {
      "id": 289,
      "image": "289.jpg",
      "rating": 6.8,
      "language": "hindi",
      "year": 2004
    },
    {
      "id": 290,
      "image": "290.jpg",
      "rating": 8.7,
      "language": "hindi",
      "year": 2010
    },
    {
      "id": 291,
      "image": "291.jpg",
      "rating": 7.5,
      "language": "hindi",
      "year": 2016
    },
    {
      "id": 292,
      "image": "292.jpg",
      "rating": 9.2,
      "language": "hindi",
      "year": 2002
    },
    {
      "id": 293,
      "image": "293.jpg",
      "rating": 6.7,
      "language": "hindi",
      "year": 2023
    },
    {
      "id": 294,
      "image": "294.jpg",
      "rating": 8.4,
      "language": "hindi",
      "year": 2009
    },
    {
      "id": 295,
      "image": "295.jpg",
      "rating": 7.9,
      "language": "hindi",
      "year": 2015
    },
    {
      "id": 296,
      "image": "296.jpg",
      "rating": 6.6,
      "language": "hindi",
      "year": 2001
    },
    {
      "id": 297,
      "image": "297.jpg",
      "rating": 8.8,
      "language": "hindi",
      "year": 1998
    },
    {
      "id": 298,
      "image": "298.jpg",
      "rating": 7.4,
      "language": "hindi",
      "year": 2000
    },
    {
      "id": 299,
      "image": "299.jpg",
      "rating": 9.0,
      "language": "hindi",
      "year": 1999
    },
    {
      "id": 300,
      "image": "300.jpg",
      "rating": 6.8,
      "language": "hindi",
      "year": 2012
    },
    {
      "id": 301,
      "image": "301.jpg",
      "rating": 8.5,
      "language": "hindi",
      "year": 2019
    },
    {
      "id": 302,
      "image": "302.jpg",
      "rating": 7.7,
      "language": "hindi",
      "year": 2021
    },
    {
      "id": 303,
      "image": "303.jpg",
      "rating": 6.9,
      "language": "hindi",
      "year": 2005
    },
    {
      "id": 304,
      "image": "304.jpg",
      "rating": 8.6,
      "language": "hindi",
      "year": 2018
    },
    {
      "id": 305,
      "image": "305.jpg",
      "rating": 7.3,
      "language": "hindi",
      "year": 2024
    },
    {
      "id": 306,
      "image": "306.jpg",
      "rating": 9.1,
      "language": "hindi",
      "year": 2007
    },
    {
      "id": 307,
      "image": "307.jpg",
      "rating": 6.7,
      "language": "hindi",
      "year": 2014
    },
    {
      "id": 308,
      "image": "308.jpg",
      "rating": 8.2,
      "language": "hindi",
      "year": 2020
    }
  ]
}
